cfcf/__init__.py
cfcf/cfcf.py
cfcf-0.1.0.dist-info/LICENSE
cfcf-0.1.0.dist-info/METADATA
cfcf-0.1.0.dist-info/WHEEL
cfcf-0.1.0.dist-info/top_level.txt
cfcf-0.1.0.dist-info/RECORD
