Metadata-Version: 2.1
Name: cfcf
Version: 0.1.0
Summary: collision-free cache folder
Home-page: https://github.com/tkmnet/cfcf
Author: tkms
Author-email: tkmnet.dev@gmail.com
License: UNKNOWN
Platform: UNKNOWN
Requires-Dist: ulid-py
